media_tools/__init__.py
media_tools/backup_lastfm_data.py
media_tools/buy_most_played.py
media_tools/clean_filenames.py
media_tools/copy_from_playlist.py
media_tools/mixcloud_upload.py
media_tools/play_time.py
media_tools/util/__init__.py
media_tools/util/audacious_tools.py
media_tools/util/base_filename_cleaner.py
media_tools/util/buying/__init__.py
media_tools/util/buying/distributor.py
media_tools/util/buying/last_fm.py
media_tools/util/buying/retry_http.py
media_tools/util/buying/track.py
media_tools/util/buying/trackdb.py
media_tools/util/command.py
media_tools/util/dump_data.py
media_tools/util/duplicate_string_remover.py
media_tools/util/extension_lowercaser.py
media_tools/util/junk_remover.py
media_tools/util/lastfm_user.py
media_tools/util/length_reader.py
media_tools/util/logging.py
media_tools/util/media_extensions.py
media_tools/util/mixcloud/__init__.py
media_tools/util/mixcloud/authorization_error.py
media_tools/util/mixcloud/constants.py
media_tools/util/mixcloud/create_api_token.py
media_tools/util/mixcloud/globals.py
media_tools/util/mixcloud/mix.py
media_tools/util/mixcloud/mix_path.py
media_tools/util/mixcloud/multi_mix.py
media_tools/util/mixcloud/oauth_parameter_receiver.py
media_tools/util/numbering_fixer.py
media_tools/util/playlist_copier.py
media_tools/util/scrobbles.py
media_tools/util/symlink_fixer.py
media_tools/util/undo_commands.py
media_tools/util/util.py
media_tools-0.4.7.dist-info/LICENSE
media_tools-0.4.7.dist-info/METADATA
media_tools-0.4.7.dist-info/WHEEL
media_tools-0.4.7.dist-info/entry_points.txt
media_tools-0.4.7.dist-info/RECORD
