Metadata-Version: 2.1
Name: media-tools
Version: 0.4.7
Summary: Creating and managing playlists, and managing the filenames and directory structure for large numbers of music files.
Home-page: https://gitlab.com/lilacashes/music-library-tools
License: MIT
Keywords: music,audio
Author: Lene Preuss
Author-email: lene.preuss@gmail.com
Requires-Python: >=3.9,<4.0
Classifier: License :: OSI Approved :: MIT License
Classifier: Programming Language :: Python :: 3
Classifier: Programming Language :: Python :: 3.9
Classifier: Programming Language :: Python :: 3.10
Classifier: Programming Language :: Python :: 3.11
Classifier: Programming Language :: Python :: 3.12
Requires-Dist: audioread (>=2.1.9)
Requires-Dist: coloredlogs (>=15.0.1)
Requires-Dist: lxml (>=4.8.0)
Requires-Dist: mutagen (>=1.45.1)
Requires-Dist: pydub (>=0.24.1)
Requires-Dist: pylast (>=5.0.0)
Requires-Dist: python-magic (>=0.4.25)
Requires-Dist: requests (>=2.27.1)
Requires-Dist: setuptools (>=68.2)
Requires-Dist: tinytag (>=1.8.1)
Project-URL: Repository, https://gitlab.com/lilacashes/music-library-tools.git
